[
  {
    "id": 4,
    "name": "Певек",
    "desc": "Лендинг порта Певек",
    "about": "",
    "href": "https://morport-pevek.ru/",
    "link": "morport-pevek.ru",
    "imageSmall": "pevek-small.jpg",
    "imageBig": "pevek.jpg",
    "skills": ["PUG, SCSS", "JavaScript"]
  },
  {
    "id": 8,
    "name": "retrova",
    "desc": "Интернет-магазин бренда",
    "about": "",
    "href": "https://eduardoalparov.github.io/accent-Retrova/index.html",
    "link": "retrova.io",
    "imageSmall": "retrova-small.jpg",
    "imageBig": "retrova.jpg",
    "skills": ["HTML, CSS", "JavaScript"]
  },
  {
    "id": 8,
    "name": "Checking Carriers",
    "desc": "Сайт юридической проверки авто",
    "about": "",
    "href": "https://info.checking-carriers.ru/",
    "link": "info.checking-carriers.ru",
    "imageSmall": "checking-small.jpg",
    "imageBig": "checking.jpg",
    "skills": ["HTML, CSS", "JavaScript"]
  },
  {
    "id": 1,
    "name": "Ангар-Строй",
    "desc": "Лендинг производства ангаров",
    "about": "",
    "href": "https://eduardoalparov.github.io/accent-Hangar",
    "link": "accent-hangar.io",
    "imageSmall": "hangar-small.jpg",
    "imageBig": "hangar.jpg",
    "skills": ["HTML, CSS", "JavaScript, jQuery"]
  },
  {
    "id": 1,
    "name": "Neon-art",
    "desc": "Корпоративный сайт рекламного агентства",
    "about": "",
    "href": "https://www.neonart.ru/lp/jobs/",
    "link": "www.neonart.ru",
    "imageSmall": "neonart-small.jpg",
    "imageBig": "neonart.jpg",
    "skills": ["HTML, CSS", "JavaScript, jQuery"]
  },
  {
    "id": 7,
    "name": "ПРОФСНАБ",
    "desc": "Сайт для компании 'ПРОФСНАБ'",
    "about": "",
    "href": "https://pk-profsnab.ru/",
    "link": "pk-profsnab.ru",
    "imageSmall": "profsnab-small.jpg",
    "imageBig": "profsnab.jpg",
    "skills": ["HTML, CSS", "JavaScript"]
  },
  {
    "id": 1,
    "name": "optimus",
    "desc": "Лендинг для магазина мебели",
    "about": "",
    "href": "https://optimusbed.ru/",
    "link": "optimusbed.ru",
    "imageSmall": "optimus-small.jpg",
    "imageBig": "optimus.jpg",
    "skills": ["HTML, CSS", "JavaScript, jQuery"]
  },
  {
    "id": 6,
    "name": "СпецТехника",
    "desc": "Сайт для компании OOO 'СпецТехника'",
    "about": "",
    "href": "https://eduardoalparov.github.io/spectechnika/",
    "link": "spectechnika.io",
    "imageSmall": "spectechnika-small.jpg",
    "imageBig": "spectechnika.jpg",
    "skills": ["PUG, SCSS", "JavaScript"]
  }
]
